README.md
setup.py
kbitools/__init__.py
kbitools/flags.py
kbitools/kbi_logger.py
kbitools/klient.py
kbitools.egg-info/PKG-INFO
kbitools.egg-info/SOURCES.txt
kbitools.egg-info/dependency_links.txt
kbitools.egg-info/entry_points.txt
kbitools.egg-info/requires.txt
kbitools.egg-info/top_level.txt